pirt/README.md
pirt/__init__.py
pirt/_utils.py
pirt/deformvis.py
pirt/experiment.py
pirt/fitting.py
pirt/gaussfun.py
pirt/new_pointset.py
pirt/pyramid.py
pirt/randomdeformations.py
pirt/testing.py
pirt/apps/__init__.py
pirt/apps/deform_by_hand.py
pirt/apps/spline_by_hand.py
pirt/deform/__init__.py
pirt/deform/_deformbase.py
pirt/deform/_deformfield.py
pirt/deform/_deformgrid.py
pirt/deform/_subs.py
pirt/interp/__init__.py
pirt/interp/_backward.py
pirt/interp/_backward_cuda.py
pirt/interp/_cubic.py
pirt/interp/_forward.py
pirt/interp/_func.py
pirt/interp/_misc.py
pirt/interp/_sliceinvolume.py
pirt/reg/__init__.py
pirt/reg/reg_base.py
pirt/reg/reg_demons.py
pirt/reg/reg_elastix.py
pirt/reg/reg_gravity.py
pirt/splinegrid/__init__.py
pirt/splinegrid/_splinegridclasses.py
pirt/splinegrid/_splinegridfuncs.py
pirt-2.1.1.dist-info/LICENSE.txt
pirt-2.1.1.dist-info/WHEEL
pirt-2.1.1.dist-info/METADATA
pirt-2.1.1.dist-info/RECORD
