Metadata-Version: 2.1
Name: pirt
Version: 2.1.1
Summary: Pirt - Python Image Registration Toolkit 
Home-page: https://github.com/almarklein/pirt
Author: Almar Klein
Author-email: almar.klein@gmail.com
Requires-Python: >=3
Classifier: License :: OSI Approved :: BSD License
Classifier: Development Status :: 4 - Beta
Classifier: Programming Language :: Python :: 3
Classifier: Intended Audience :: Science/Research
Classifier: Topic :: Scientific/Engineering :: Image Recognition
Classifier: Topic :: Scientific/Engineering :: Medical Science Apps.
Classifier: Topic :: Scientific/Engineering :: Visualization
Requires-Dist: numpy
Requires-Dist: scipy
Requires-Dist: numba
Requires-Dist: visvis
